{"_type":"export","__export_format":4,"__export_date":"2023-05-30T19:12:17.820Z","__export_source":"insomnia.desktop.app:v2023.2.2","resources":[{"_id":"req_19cfb2aa35ad46a487fa672a139539ca","parentId":"fld_158612cb56264fe7b83b816331db2eda","modified":1685472890114,"created":1685197802555,"url":"{{ _.baseUrl }}/proprietarios","name":"listar","description":"","method":"GET","body":{},"parameters":[],"headers":[],"authentication":{},"metaSortKey":-1685197737461.75,"isPrivate":false,"settingStoreCookies":true,"settingSendCookies":true,"settingDisableRenderRequestBody":false,"settingEncodeUrl":true,"settingRebuildPath":true,"settingFollowRedirects":"global","_type":"request"},{"_id":"fld_158612cb56264fe7b83b816331db2eda","parentId":"wrk_1c04dfd9a62f4427b9d7074bd433254f","modified":1685197737468,"created":1685197737468,"name":"Proprietario","description":"","environment":{},"environmentPropertyOrder":null,"metaSortKey":-1685197737468,"_type":"request_group"},{"_id":"wrk_1c04dfd9a62f4427b9d7074bd433254f","parentId":null,"modified":1685197715652,"created":1685197715652,"name":"API - Alga Transito","description":"","scope":"collection","_type":"workspace"},{"_id":"req_7b235b5a21ba4709aaec186c75410f29","parentId":"fld_158612cb56264fe7b83b816331db2eda","modified":1685473481271,"created":1685469255496,"url":"{{ _.baseUrl }}/proprietarios","name":"Inserir","description":"","method":"POST","body":{"mimeType":"application/json","text":"\t{\t\t\n\t\t\"nome\": \"Chico\",\n\t\t\"email\": \"chico@example.com\",\n\t\t\"telefone\": \"85902900\"\n\t},"},"parameters":[],"headers":[{"name":"Content-Type","value":"application/json"}],"authentication":{},"metaSortKey":-1685197737411.75,"isPrivate":false,"settingStoreCookies":true,"settingSendCookies":true,"settingDisableRenderRequestBody":false,"settingEncodeUrl":true,"settingRebuildPath":true,"settingFollowRedirects":"global","_type":"request"},{"_id":"req_9626006730794041ae6a8baf9fed00ae","parentId":"fld_158612cb56264fe7b83b816331db2eda","modified":1685473818575,"created":1685469904421,"url":"{{ _.baseUrl }}/proprietarios/1","name":"Alterar","description":"","method":"PUT","body":{"mimeType":"application/json","text":"\t{\t\t\n\t\"nome\": \"Zézinho\",\n\t\"email\": \"zezinho@gmail.com\",\n\t\"telefone\": \"85902900\"\n\t}"},"parameters":[],"headers":[{"name":"Content-Type","value":"application/json"}],"authentication":{},"metaSortKey":-1685197737361.75,"isPrivate":false,"settingStoreCookies":true,"settingSendCookies":true,"settingDisableRenderRequestBody":false,"settingEncodeUrl":true,"settingRebuildPath":true,"settingFollowRedirects":"global","_type":"request"},{"_id":"req_a3f7473cedfd4fcbb22cc979be5fc10b","parentId":"fld_158612cb56264fe7b83b816331db2eda","modified":1685473899015,"created":1685473893211,"url":"{{ _.baseUrl }}/proprietarios/1","name":"Deletar","description":"","method":"DELETE","body":{},"parameters":[],"headers":[],"authentication":{},"metaSortKey":-1685197737336.75,"isPrivate":false,"settingStoreCookies":true,"settingSendCookies":true,"settingDisableRenderRequestBody":false,"settingEncodeUrl":true,"settingRebuildPath":true,"settingFollowRedirects":"global","_type":"request"},{"_id":"req_fd1eb147b5f5445080d14442830d3906","parentId":"fld_158612cb56264fe7b83b816331db2eda","modified":1685473491661,"created":1685468113079,"url":"{{ _.baseUrl }}/proprietarios/31","name":"buscar por id","description":"","method":"GET","body":{},"parameters":[],"headers":[],"authentication":{},"metaSortKey":-1685197737311.75,"isPrivate":false,"settingStoreCookies":true,"settingSendCookies":true,"settingDisableRenderRequestBody":false,"settingEncodeUrl":true,"settingRebuildPath":true,"settingFollowRedirects":"global","_type":"request"},{"_id":"env_d1e7a1ffe655d06a5990bec2562e5ca038b858b6","parentId":"wrk_1c04dfd9a62f4427b9d7074bd433254f","modified":1685197797808,"created":1685197715661,"name":"Base Environment","data":{"baseUrl":"http://localhost:8080"},"dataPropertyOrder":{"&":["baseUrl"]},"color":null,"isPrivate":false,"metaSortKey":1685197715661,"_type":"environment"},{"_id":"jar_d1e7a1ffe655d06a5990bec2562e5ca038b858b6","parentId":"wrk_1c04dfd9a62f4427b9d7074bd433254f","modified":1685197715673,"created":1685197715673,"name":"Default Jar","cookies":[],"_type":"cookie_jar"},{"_id":"spc_2d8fafd980a34a388c290a22a168b4e7","parentId":"wrk_1c04dfd9a62f4427b9d7074bd433254f","modified":1685197715653,"created":1685197715653,"fileName":"API - Alga Transito","contents":"","contentType":"yaml","_type":"api_spec"}]}